Metadata-Version: 2.4
Name: medscan-cu116
Version: 0.1.2
Summary: Medscan with CUDA 11.6 (PyTorch GPU support)
Author-email: Cristo van den Berg <cristo99@live.nl>
Project-URL: Homepage, https://github.com/CristovdBerg/medscan
Requires-Python: >=3.10
Requires-Dist: pandas==2.2.3
Requires-Dist: pyyaml==6.0.2
Requires-Dist: scikit-learn==1.6.1
Requires-Dist: scipy==1.15.3
Requires-Dist: numpy==2.1.2
Requires-Dist: matplotlib==3.10.3
Requires-Dist: torch==1.13.1+cu116
Requires-Dist: torchvision==0.13.1+cu116
Requires-Dist: torchaudio==0.12.1+cu116
Requires-Dist: triton<4.0.0,==3.2.0
Requires-Dist: fsspec==2024.6.1
Requires-Dist: pillow==11.0.0
Requires-Dist: openpyxl==3.1.5
Requires-Dist: joblib==1.5.1
Requires-Dist: networkx==3.3
Provides-Extra: dev
Requires-Dist: pytest>=8.2; extra == "dev"
Requires-Dist: ipykernel; extra == "dev"
Requires-Dist: jupyter_client; extra == "dev"
Requires-Dist: debugpy; extra == "dev"
Requires-Dist: pre-commit; extra == "dev"
